generativepy/__init__.py
generativepy/analytics.py
generativepy/bitmap.py
generativepy/color.py
generativepy/drawing.py
generativepy/drawing3d.py
generativepy/formulas.py
generativepy/geometry.py
generativepy/geometry3d.py
generativepy/gif.py
generativepy/graph.py
generativepy/math.py
generativepy/movie.py
generativepy/nparray.py
generativepy/povray.py
generativepy/shape2d.py
generativepy/table.py
generativepy/tween.py
generativepy/utils.py
generativepy-24.11.dist-info/LICENSE
generativepy-24.11.dist-info/METADATA
generativepy-24.11.dist-info/WHEEL
generativepy-24.11.dist-info/top_level.txt
generativepy-24.11.dist-info/RECORD
