Metadata-Version: 2.1
Name: generativepy
Version: 24.11
Summary: Generative art library
Home-page: https://github.com/martinmcbride/generativepy
Author: Martin McBride
Author-email: mcbride.martin@gmail.com
License: MIT
Classifier: Programming Language :: Python :: 3
Classifier: License :: OSI Approved :: MIT License
Classifier: Operating System :: OS Independent
License-File: LICENSE
Requires-Dist: numpy>=1.21.2
Requires-Dist: pycairo>=1.20.1
